backtrace.py
backtrace-0.2.1.dist-info/DESCRIPTION.rst
backtrace-0.2.1.dist-info/LICENSE.txt
backtrace-0.2.1.dist-info/METADATA
backtrace-0.2.1.dist-info/RECORD
backtrace-0.2.1.dist-info/WHEEL
backtrace-0.2.1.dist-info/entry_points.txt
backtrace-0.2.1.dist-info/metadata.json
backtrace-0.2.1.dist-info/top_level.txt
