Metadata-Version: 1.1
Name: backtrace
Version: 0.2.1
Summary: Makes tracebacks humanly readable
Home-page: https://github.com/nir0s/backtrace
Author: nir0s
Author-email: nir36g@gmail.com
License: LICENSE
Platform: All
Classifier: Programming Language :: Python
Classifier: Programming Language :: Python :: 2.7
Classifier: Programming Language :: Python :: 3.4
Classifier: Programming Language :: Python :: 3.5
Classifier: Programming Language :: Python :: 3.6
Classifier: Natural Language :: English
Classifier: Environment :: Console
Classifier: Intended Audience :: Developers
Classifier: Intended Audience :: Information Technology
Classifier: Intended Audience :: System Administrators
Classifier: License :: OSI Approved :: Apache Software License
Classifier: Operating System :: POSIX :: Linux
Classifier: Operating System :: Microsoft
Classifier: Topic :: Software Development :: Libraries :: Python Modules
